xia_engine_cypher/__init__.py
xia_engine_cypher/engine.cp310-win_amd64.pyd
xia_engine_cypher-0.0.5.dist-info/LICENSE.txt
xia_engine_cypher-0.0.5.dist-info/METADATA
xia_engine_cypher-0.0.5.dist-info/WHEEL
xia_engine_cypher-0.0.5.dist-info/top_level.txt
xia_engine_cypher-0.0.5.dist-info/RECORD
