Metadata-Version: 2.1
Name: xia-engine-cypher
Version: 0.0.5
Home-page: https://develop.x-i-a.com/docs/xia-engine-cypher/0.0.5/index.html
Author: X-I-A
Author-email: admin@x-i-a.com
Requires-Python: >=3.9
License-File: LICENSE.txt
Requires-Dist: xia-fields
Requires-Dist: xia-engine
